syft_job/__init__.py
syft_job/client.py
syft_job/config.py
syft_job/job_runner.py
syft_job/runner_main.py
syft_job-0.1.23.dist-info/METADATA
syft_job-0.1.23.dist-info/WHEEL
syft_job-0.1.23.dist-info/entry_points.txt
syft_job-0.1.23.dist-info/RECORD
