Metadata-Version: 2.4
Name: syft-job
Version: 0.1.23
Summary: Add your description here
Requires-Python: >=3.12
Requires-Dist: pandas
Requires-Dist: pydantic>=2.11.7
Requires-Dist: pyyaml>=6.0
